wiki_music/__init__.py
wiki_music/app_cli.py
wiki_music/app_gui.py
wiki_music/profiler.py
wiki_music/version.py
wiki_music/constants/__init__.py
wiki_music/constants/colors.py
wiki_music/constants/gui_const.py
wiki_music/constants/parser_const.py
wiki_music/constants/paths.py
wiki_music/constants/tags.py
wiki_music/external_libraries/__init__.py
wiki_music/external_libraries/google_images_download/__init__.py
wiki_music/external_libraries/google_images_download/__main__.py
wiki_music/external_libraries/google_images_download/google_images_download.py
wiki_music/external_libraries/google_images_download/google_images_download_offline.py
wiki_music/external_libraries/lyricsfinder/__init__.py
wiki_music/external_libraries/lyricsfinder/extractor.py
wiki_music/external_libraries/lyricsfinder/lyrics.py
wiki_music/external_libraries/lyricsfinder/utils.py
wiki_music/external_libraries/lyricsfinder/extractors/__init__.py
wiki_music/external_libraries/lyricsfinder/extractors/animelyrics.py
wiki_music/external_libraries/lyricsfinder/extractors/azlyrics.py
wiki_music/external_libraries/lyricsfinder/extractors/darklyrics.py
wiki_music/external_libraries/lyricsfinder/extractors/genius.py
wiki_music/external_libraries/lyricsfinder/extractors/lyrical_nonsense.py
wiki_music/external_libraries/lyricsfinder/extractors/lyricsmode.py
wiki_music/external_libraries/lyricsfinder/extractors/musixmatch.py
wiki_music/external_libraries/lyricsfinder/models/__init__.py
wiki_music/external_libraries/lyricsfinder/models/exceptions.py
wiki_music/external_libraries/lyricsfinder/models/lyrics.py
wiki_music/files/Na.jpg
wiki_music/files/icon.ico
wiki_music/files/settings.yml
wiki_music/gui_lib/__init__.py
wiki_music/gui_lib/base.py
wiki_music/gui_lib/cover_art.py
wiki_music/gui_lib/custom_classes.py
wiki_music/gui_lib/data_model.py
wiki_music/gui_lib/main_window.py
wiki_music/gui_lib/qt_importer.py
wiki_music/library/__init__.py
wiki_music/library/lyrics.py
wiki_music/library/tags_io.py
wiki_music-0.6a0.dist-info/LICENSE.txt
wiki_music-0.6a0.dist-info/METADATA
wiki_music-0.6a0.dist-info/WHEEL
wiki_music-0.6a0.dist-info/entry_points.txt
wiki_music-0.6a0.dist-info/top_level.txt
wiki_music-0.6a0.dist-info/RECORD
