Metadata-Version: 2.1
Name: wiki-music
Version: 0.6a0
Summary: Music tagger with information retrieval from wikipedia
Home-page: https://github.com/marian-code/wikipedia-music-tags
Author: Marián Rynik
Author-email: marian.rynik@outlook.sk
License: MIT
Keywords: tagging music tags wikipedia
Platform: UNKNOWN
Classifier: Development Status :: 3 - Alpha
Classifier: Operating System :: OS Independent
Classifier: Intended Audience :: Developers
Classifier: Intended Audience :: End Users/Desktop
Classifier: Environment :: Console
Classifier: Environment :: MacOS X
Classifier: Environment :: X11 Applications :: Qt
Classifier: Natural Language :: English
Classifier: License :: OSI Approved :: MIT License
Classifier: Programming Language :: Python :: 3.6
Classifier: Programming Language :: Python :: 3.7
Classifier: Programming Language :: Python :: 3.8
Classifier: Topic :: Multimedia :: Sound/Audio :: Analysis
Classifier: Typing :: Typed
Requires-Python: >=3.6
Requires-Dist: appdirs (>=1.4.3)
Requires-Dist: beautifulsoup4 (>=4.6.0)
Requires-Dist: colorama (>=0.4.0)
Requires-Dist: datefinder (>=0.6.1)
Requires-Dist: fuzzywuzzy (>=0.17.0)
Requires-Dist: lazy-import (>=0.2.2)
Requires-Dist: lxml (>=4.2.1)
Requires-Dist: nltk (>=3.3)
Requires-Dist: mutagen (>=1.42.0)
Requires-Dist: numpy (>=1.14.3)
Requires-Dist: Pillow (>=6.1.0)
Requires-Dist: pyyaml (>=5.1.2)
Requires-Dist: PyQt5 (>=5.11.3)
Requires-Dist: python-Levenshtein (>=0.12.0)
Requires-Dist: QtPy (>=1.7.0)
Requires-Dist: requests (>=2.18.4)
Requires-Dist: wikipedia (>=1.4.0)
Provides-Extra: test
Requires-Dist: unittest ; extra == 'test'
Requires-Dist: appdirs (>=1.4.3) ; extra == 'test'
Requires-Dist: beautifulsoup4 (>=4.6.0) ; extra == 'test'
Requires-Dist: colorama (>=0.4.0) ; extra == 'test'
Requires-Dist: datefinder (>=0.6.1) ; extra == 'test'
Requires-Dist: fuzzywuzzy (>=0.17.0) ; extra == 'test'
Requires-Dist: lazy-import (>=0.2.2) ; extra == 'test'
Requires-Dist: lxml (>=4.2.1) ; extra == 'test'
Requires-Dist: nltk (>=3.3) ; extra == 'test'
Requires-Dist: mutagen (>=1.42.0) ; extra == 'test'
Requires-Dist: numpy (>=1.14.3) ; extra == 'test'
Requires-Dist: Pillow (>=6.1.0) ; extra == 'test'
Requires-Dist: pyyaml (>=5.1.2) ; extra == 'test'
Requires-Dist: PyQt5 (>=5.11.3) ; extra == 'test'
Requires-Dist: python-Levenshtein (>=0.12.0) ; extra == 'test'
Requires-Dist: QtPy (>=1.7.0) ; extra == 'test'
Requires-Dist: requests (>=2.18.4) ; extra == 'test'
Requires-Dist: wikipedia (>=1.4.0) ; extra == 'test'
